<?xml version="1.0" encoding="utf-8"?><toc><breadcrumbs><li><a href="d75eb659-6335-53f6-af7a-81814a21ab7f.htm">Docs</a></li><li><a href="d75eb659-6335-53f6-af7a-81814a21ab7f.htm">Manual del programador</a></li><li><a href="9031ec78-66ca-d43c-d6b3-17e611b1c695.htm">SERVICE Namespaces</a></li><li><a href="db2f69b3-eb33-fe50-28af-e03f9d29f15e.htm">SERVICE.<wbr />DAL Namespaces</a></li><li><a href="ef651164-e912-fcd9-e01b-a63ad62db965.htm">SERVICE.<wbr />DAL.<wbr />Implementations Namespaces</a></li><li><a href="2d0b7fa9-93e6-1c0d-c913-cc1c2a5d3683.htm">SERVICE.<wbr />DAL.<wbr />Implementations</a></li></breadcrumbs><tocItems><li><a id="06bf263f-fd1b-4226-e56f-dd728ea6d805" class="has-submenu" href="06bf263f-fd1b-4226-e56f-dd728ea6d805.htm"><span data-tocFile="../toc/IDAADAEA.xml" class="icon toggle" onclick="ToggleExpandCollapse(this); return false;"><i class="fa fa-angle-right"> </i></span>Backup<wbr />Repository</a><ul class="toc-menu is-hidden"> </ul></li><li><a id="fa58b6ad-c67b-9fa0-2e3f-20ee80aa81b4" class="has-submenu" href="fa58b6ad-c67b-9fa0-2e3f-20ee80aa81b4.htm"><span data-tocFile="../toc/IDBADAEA.xml" class="icon toggle" onclick="ToggleExpandCollapse(this); return false;"><i class="fa fa-angle-right"> </i></span>Bitacora<wbr />Respository</a><ul class="toc-menu is-hidden"> </ul></li><li><a id="b9720c51-71de-1644-5bce-8449e9a879f8" class="has-submenu" href="b9720c51-71de-1644-5bce-8449e9a879f8.htm"><span data-tocFile="../toc/IDCADAEA.xml" class="icon toggle" onclick="ToggleExpandCollapse(this); return false;"><i class="fa fa-angle-right"> </i></span>Familia<wbr />Patente<wbr />Repository</a><ul class="toc-menu is-hidden"> </ul></li><li><a id="e26872e8-2818-c6bb-b372-eb434de46bb0" class="has-submenu" href="e26872e8-2818-c6bb-b372-eb434de46bb0.htm"><span data-tocFile="../toc/IDDADAEA.xml" class="icon toggle" onclick="ToggleExpandCollapse(this); return false;"><i class="fa fa-angle-right"> </i></span>Familia<wbr />Repository</a><ul class="toc-menu is-hidden"> </ul></li><li><a id="af784d86-0615-4c2b-ec6a-086534e468e7" class="has-submenu" href="af784d86-0615-4c2b-ec6a-086534e468e7.htm"><span data-tocFile="../toc/IDEADAEA.xml" class="icon toggle" onclick="ToggleExpandCollapse(this); return false;"><i class="fa fa-angle-right"> </i></span>Language<wbr />Repository</a><ul class="toc-menu is-hidden"> </ul></li><li><a id="d7fd25b3-27bc-a534-de94-61e21c52aa3f" class="has-submenu" href="d7fd25b3-27bc-a534-de94-61e21c52aa3f.htm"><span data-tocFile="../toc/IDFADAEA.xml" class="icon toggle" onclick="ToggleExpandCollapse(this); return false;"><i class="fa fa-angle-right"> </i></span>Patente<wbr />Repository</a><ul class="toc-menu is-hidden"> </ul></li><li><a id="f415bfc6-1b23-6bde-10b7-5f5ee28b68e0" class="has-submenu" href="f415bfc6-1b23-6bde-10b7-5f5ee28b68e0.htm"><span data-tocFile="../toc/IDGADAEA.xml" class="icon toggle" onclick="ToggleExpandCollapse(this); return false;"><i class="fa fa-angle-right"> </i></span>Usuario<wbr />Familia<wbr />Repository</a><ul class="toc-menu is-hidden"> </ul></li><li><a id="84c2738a-e4cf-2090-ec66-cf923c609acf" class="has-submenu" href="84c2738a-e4cf-2090-ec66-cf923c609acf.htm"><span data-tocFile="../toc/IDHADAEA.xml" class="icon toggle" onclick="ToggleExpandCollapse(this); return false;"><i class="fa fa-angle-right"> </i></span>Usuario<wbr />Patente<wbr />Repository</a><ul class="toc-menu is-hidden"> </ul></li><li><a id="1fd693d1-483d-f1c7-3e05-8d84ec876656" class="has-submenu" href="1fd693d1-483d-f1c7-3e05-8d84ec876656.htm"><span data-tocFile="../toc/IDIADAEA.xml" class="icon toggle" onclick="ToggleExpandCollapse(this); return false;"><i class="fa fa-angle-right"> </i></span>Usuario<wbr />Repository</a><ul class="toc-menu is-hidden"> </ul></li></tocItems></toc>